shotfirst/__init__.py
shotfirst/app.py
shotfirst/handlers.py
shotfirst-0.12.3.dist-info/LICENSE
shotfirst-0.12.3.dist-info/METADATA
shotfirst-0.12.3.dist-info/WHEEL
shotfirst-0.12.3.dist-info/entry_points.txt
shotfirst-0.12.3.dist-info/RECORD
