Metadata-Version: 2.1
Name: shotfirst
Version: 0.12.3
Summary: Monitor a number of directories for files and copy/move them
Home-page: https://gitlab.com/kad/shotfirst
License: MIT
Keywords: inotify,backup
Author: Jorge Gallegos
Author-email: kad@blegh.net
Requires-Python: >=3.10,<4.0
Classifier: Development Status :: 4 - Beta
Classifier: Environment :: Console
Classifier: License :: OSI Approved :: MIT License
Classifier: Operating System :: POSIX :: Linux
Classifier: Programming Language :: Python :: 3
Classifier: Programming Language :: Python :: 3.10
Classifier: Programming Language :: Python :: 3.11
Classifier: Programming Language :: Python :: 3.12
Classifier: Topic :: System :: Archiving :: Backup
Classifier: Topic :: Utilities
Requires-Dist: enzyme (>=0.4.1,<0.5.0)
Requires-Dist: pdfrw (>=0.4,<0.5)
Requires-Dist: pillow (>=10.2.0,<11.0.0)
Requires-Dist: pyinotify (>=0.9.6,<0.10.0)
